canto_filter-1.1.4.dist-info/licenses/LICENSE
cantofilter/__init__.py
cantofilter/cli.py
cantofilter/judge.py
cantofilter/version.py
tests/__init__.py
tests/test_judge.py
canto_filter-1.1.4.dist-info/METADATA
canto_filter-1.1.4.dist-info/WHEEL
canto_filter-1.1.4.dist-info/entry_points.txt
canto_filter-1.1.4.dist-info/top_level.txt
canto_filter-1.1.4.dist-info/RECORD
