Metadata-Version: 2.4
Name: canto-filter
Version: 1.1.4
Summary: 粵文分類篩選器 Cantonese text filter
Author: CanCLID (Cantonese Computational Linguistics Infrastructure Development Workgroup)
Author-email: support@jyutping.org
Classifier: Programming Language :: Python :: 3
Classifier: Programming Language :: Python :: 3.11
Classifier: Programming Language :: Python :: 3.12
Classifier: License :: OSI Approved :: MIT License
Classifier: Intended Audience :: Developers
Classifier: Topic :: Text Processing :: Linguistic
Classifier: Natural Language :: Cantonese
Classifier: Operating System :: OS Independent
Requires-Python: >=3.11
License-File: LICENSE
Dynamic: author
Dynamic: author-email
Dynamic: classifier
Dynamic: description
Dynamic: description-content-type
Dynamic: license-file
Dynamic: requires-python
Dynamic: summary
